extra_keywords
tests
