Metadata-Version: 1.1
Name: django-extra-keywords
Version: 1.1.2
Summary: Extra gettext keywords handling in Django
Home-page: https://bitbucket.org/tkhyn/django-extra_keywords
Author: Thomas Khyn
Author-email: thomas@ksytek.com
License: UNKNOWN
Keywords: i18n,translation,gettext,keywords
Platform: UNKNOWN
Classifier: Programming Language :: Python
Classifier: Programming Language :: Python :: 2.6
Classifier: Programming Language :: Python :: 2.7
Classifier: Programming Language :: Python :: 3.3
Classifier: Programming Language :: Python :: 3.4
Classifier: License :: OSI Approved :: MIT License
Classifier: Operating System :: OS Independent
Classifier: Development Status :: 5 - Production/Stable
Classifier: Intended Audience :: Developers
Classifier: Framework :: Django
Classifier: Environment :: Plugins
Classifier: Topic :: Software Development :: Internationalization
Classifier: Topic :: Software Development :: Libraries :: Python Modules
Classifier: Topic :: Text Processing :: Linguistic
